{
  "count": 3,
  "data": [
    {
      "Invoice_ID": "2292522",
      "Event_Name": "Cleveland Browns vs Jacksonville Jaguars ",
      "Event_Date": "2017-11-19 00:00:00",
      "ticket_total": "76.0",
      "discount_total": "0.0",
      "shipping_total": "0.0",
      "handling_total": "11.400000452995",
      "invoice_total": "87.400000452995002",
      "HasPDF": "1",
      "HasMobile": "0",
      "in_hand_date": null,
      "apponly": "0",
      "app_only_type": "not_apponly",
      "app_only_link": null,
      "order_status": "Completed"
    },
    {
      "Invoice_ID": "2292523",
      "Event_Name": "Boston Celtics vs New Orleans Pelicans",
      "Event_Date": "2018-01-16 00:00:00",
      "ticket_total": "50.0",
      "discount_total": "0.0",
      "shipping_total": "0.0",
      "handling_total": "9.9799995422362997",
      "invoice_total": "59.9799995422363",
      "HasPDF": "0",
      "HasMobile": "1",
      "in_hand_date": null,
      "apponly": "0",
      "app_only_type": "not_apponly",
      "app_only_link": null,
      "order_status": "In Progress"
    },
    {
      "Invoice_ID": "2292524",
      "Event_Name": "Boston Celtics vs New Orleans Pelicans",
      "Event_Date": "2018-01-16 00:00:00",
      "ticket_total": "60.0",
      "discount_total": "0.0",
      "shipping_total": "0.0",
      "handling_total": "9.9799995422362997",
      "invoice_total": "69.9799995422363",
      "HasPDF": "0",
      "HasMobile": "0",
      "in_hand_date": null,
      "apponly": "1",
      "app_only_type": "tm_link",
      "app_only_link": "https://www.aceticket.com/download/2292524",
      "order_status": "In Progress"
    }
  ]
}